{
    "folder": "367",
    "audio_files": [
        {
            "file": "367_1.wav",
            "duration": 34.24
        },
        {
            "file": "367_2.wav",
            "duration": 29.69
        },
        {
            "file": "367_3.wav",
            "duration": 32.57
        },
        {
            "file": "367_4.wav",
            "duration": 29.61
        },
        {
            "file": "367_5.wav",
            "duration": 28.07
        },
        {
            "file": "367_6.wav",
            "duration": 19.53
        },
        {
            "file": "367_7.wav",
            "duration": 32.81
        },
        {
            "file": "367_8.wav",
            "duration": 28.34
        },
        {
            "file": "367_9.wav",
            "duration": 35.95
        },
        {
            "file": "367_10.wav",
            "duration": 33.83
        },
        {
            "file": "367_11.wav",
            "duration": 33.49
        },
        {
            "file": "367_12.wav",
            "duration": 33.56
        },
        {
            "file": "367_13.wav",
            "duration": 28.07
        },
        {
            "file": "367_14.wav",
            "duration": 31.76
        },
        {
            "file": "367_15.wav",
            "duration": 28.47
        },
        {
            "file": "367_16.wav",
            "duration": 31.42
        },
        {
            "file": "367_17.wav",
            "duration": 30.91
        },
        {
            "file": "367_18.wav",
            "duration": 32.67
        },
        {
            "file": "367_19.wav",
            "duration": 33.04
        },
        {
            "file": "367_20.wav",
            "duration": 31.18
        },
        {
            "file": "367_21.wav",
            "duration": 35.46
        },
        {
            "file": "367_22.wav",
            "duration": 28.78
        },
        {
            "file": "367_23.wav",
            "duration": 30.66
        }
    ],
    "total_files": 23,
    "total_duration": 714.11
}