{
    "folder": "396",
    "audio_files": [
        {
            "file": "396_1.mp3",
            "duration": 34.32
        },
        {
            "file": "396_2.mp3",
            "duration": 27.44
        },
        {
            "file": "396_3.mp3",
            "duration": 32.62
        },
        {
            "file": "396_4.mp3",
            "duration": 28.8
        },
        {
            "file": "396_5.mp3",
            "duration": 30.64
        },
        {
            "file": "396_6.mp3",
            "duration": 29.43
        },
        {
            "file": "396_7.mp3",
            "duration": 30.81
        },
        {
            "file": "396_8.mp3",
            "duration": 27.62
        },
        {
            "file": "396_9.mp3",
            "duration": 23.94
        },
        {
            "file": "396_10.mp3",
            "duration": 33.92
        },
        {
            "file": "396_11.mp3",
            "duration": 28.03
        },
        {
            "file": "396_12.mp3",
            "duration": 27.49
        },
        {
            "file": "396_13.mp3",
            "duration": 38.51
        },
        {
            "file": "396_14.mp3",
            "duration": 31.75
        },
        {
            "file": "396_15.mp3",
            "duration": 35.12
        },
        {
            "file": "396_16.mp3",
            "duration": 34.57
        },
        {
            "file": "396_17.mp3",
            "duration": 33.0
        },
        {
            "file": "396_18.mp3",
            "duration": 32.89
        },
        {
            "file": "396_19.mp3",
            "duration": 29.94
        },
        {
            "file": "396_20.mp3",
            "duration": 32.3
        },
        {
            "file": "396_21.mp3",
            "duration": 33.02
        },
        {
            "file": "396_22.mp3",
            "duration": 36.18
        },
        {
            "file": "396_23.mp3",
            "duration": 27.61
        },
        {
            "file": "396_24.mp3",
            "duration": 22.56
        },
        {
            "file": "396_25.mp3",
            "duration": 32.75
        },
        {
            "file": "396_26.mp3",
            "duration": 36.29
        },
        {
            "file": "396_27.mp3",
            "duration": 26.21
        },
        {
            "file": "396_28.mp3",
            "duration": 29.52
        },
        {
            "file": "396_29.mp3",
            "duration": 26.64
        },
        {
            "file": "396_30.mp3",
            "duration": 28.45
        },
        {
            "file": "396_31.mp3",
            "duration": 32.3
        },
        {
            "file": "396_32.mp3",
            "duration": 32.07
        },
        {
            "file": "396_33.mp3",
            "duration": 35.37
        },
        {
            "file": "396_34.mp3",
            "duration": 30.18
        },
        {
            "file": "396_35.mp3",
            "duration": 31.46
        },
        {
            "file": "396_36.mp3",
            "duration": 27.16
        },
        {
            "file": "396_37.mp3",
            "duration": 37.59
        },
        {
            "file": "396_38.mp3",
            "duration": 25.04
        }
    ],
    "total_files": 38,
    "total_duration": 1173.54
}