{
    "folder": "447",
    "audio_files": [
        {
            "file": "447_1.wav",
            "duration": 31.86
        },
        {
            "file": "447_2.wav",
            "duration": 34.6
        },
        {
            "file": "447_3.wav",
            "duration": 28.36
        },
        {
            "file": "447_4.wav",
            "duration": 33.59
        },
        {
            "file": "447_5.wav",
            "duration": 31.72
        },
        {
            "file": "447_6.wav",
            "duration": 33.44
        },
        {
            "file": "447_7.wav",
            "duration": 28.34
        },
        {
            "file": "447_8.wav",
            "duration": 24.68
        },
        {
            "file": "447_9.wav",
            "duration": 27.56
        },
        {
            "file": "447_10.wav",
            "duration": 30.26
        },
        {
            "file": "447_11.wav",
            "duration": 32.32
        },
        {
            "file": "447_12.wav",
            "duration": 31.69
        },
        {
            "file": "447_13.wav",
            "duration": 26.59
        },
        {
            "file": "447_14.wav",
            "duration": 34.07
        },
        {
            "file": "447_15.wav",
            "duration": 34.52
        },
        {
            "file": "447_16.wav",
            "duration": 25.6
        },
        {
            "file": "447_17.wav",
            "duration": 28.95
        },
        {
            "file": "447_18.wav",
            "duration": 27.46
        },
        {
            "file": "447_19.wav",
            "duration": 19.95
        },
        {
            "file": "447_20.wav",
            "duration": 26.83
        },
        {
            "file": "447_21.wav",
            "duration": 27.44
        },
        {
            "file": "447_22.wav",
            "duration": 35.41
        },
        {
            "file": "447_23.wav",
            "duration": 31.69
        },
        {
            "file": "447_24.wav",
            "duration": 37.42
        },
        {
            "file": "447_25.wav",
            "duration": 36.19
        },
        {
            "file": "447_26.wav",
            "duration": 30.68
        },
        {
            "file": "447_27.wav",
            "duration": 23.76
        },
        {
            "file": "447_28.wav",
            "duration": 22.74
        },
        {
            "file": "447_29.wav",
            "duration": 30.62
        },
        {
            "file": "447_30.wav",
            "duration": 30.25
        },
        {
            "file": "447_31.wav",
            "duration": 26.12
        },
        {
            "file": "447_32.wav",
            "duration": 37.58
        },
        {
            "file": "447_33.wav",
            "duration": 34.96
        },
        {
            "file": "447_34.wav",
            "duration": 26.4
        },
        {
            "file": "447_35.wav",
            "duration": 33.98
        },
        {
            "file": "447_36.wav",
            "duration": 23.79
        },
        {
            "file": "447_37.wav",
            "duration": 29.15
        },
        {
            "file": "447_38.wav",
            "duration": 29.23
        },
        {
            "file": "447_39.wav",
            "duration": 23.49
        },
        {
            "file": "447_40.wav",
            "duration": 28.73
        },
        {
            "file": "447_41.wav",
            "duration": 33.22
        },
        {
            "file": "447_42.wav",
            "duration": 36.51
        },
        {
            "file": "447_43.wav",
            "duration": 36.14
        },
        {
            "file": "447_44.wav",
            "duration": 28.95
        }
    ],
    "total_files": 44,
    "total_duration": 1326.84
}