{
    "folder": "153",
    "audio_files": [
        {
            "file": "153_1.wav",
            "duration": 34.18
        },
        {
            "file": "153_2.wav",
            "duration": 34.38
        },
        {
            "file": "153_3.wav",
            "duration": 35.2
        },
        {
            "file": "153_4.wav",
            "duration": 23.56
        },
        {
            "file": "153_5.wav",
            "duration": 37.96
        },
        {
            "file": "153_6.wav",
            "duration": 31.09
        },
        {
            "file": "153_7.wav",
            "duration": 23.9
        },
        {
            "file": "153_8.wav",
            "duration": 29.99
        },
        {
            "file": "153_9.wav",
            "duration": 31.49
        },
        {
            "file": "153_10.wav",
            "duration": 28.35
        },
        {
            "file": "153_11.wav",
            "duration": 44.59
        },
        {
            "file": "153_12.wav",
            "duration": 30.48
        },
        {
            "file": "153_13.wav",
            "duration": 29.65
        },
        {
            "file": "153_14.wav",
            "duration": 28.8
        },
        {
            "file": "153_15.wav",
            "duration": 31.09
        },
        {
            "file": "153_16.wav",
            "duration": 28.45
        },
        {
            "file": "153_17.wav",
            "duration": 32.2
        },
        {
            "file": "153_18.wav",
            "duration": 34.76
        },
        {
            "file": "153_19.wav",
            "duration": 33.26
        },
        {
            "file": "153_20.wav",
            "duration": 31.51
        },
        {
            "file": "153_21.wav",
            "duration": 31.55
        },
        {
            "file": "153_22.wav",
            "duration": 32.22
        },
        {
            "file": "153_23.wav",
            "duration": 28.16
        },
        {
            "file": "153_24.wav",
            "duration": 28.68
        },
        {
            "file": "153_25.wav",
            "duration": 30.52
        },
        {
            "file": "153_26.wav",
            "duration": 26.83
        },
        {
            "file": "153_27.wav",
            "duration": 36.49
        },
        {
            "file": "153_28.wav",
            "duration": 33.5
        },
        {
            "file": "153_29.wav",
            "duration": 16.56
        }
    ],
    "total_files": 29,
    "total_duration": 899.4
}