{
    "folder": "182",
    "audio_files": [
        {
            "file": "182_1.mp3",
            "duration": 42.78
        },
        {
            "file": "182_2.mp3",
            "duration": 27.5
        },
        {
            "file": "182_3.mp3",
            "duration": 31.74
        },
        {
            "file": "182_4.mp3",
            "duration": 32.48
        },
        {
            "file": "182_5.mp3",
            "duration": 33.12
        },
        {
            "file": "182_6.mp3",
            "duration": 36.38
        },
        {
            "file": "182_7.mp3",
            "duration": 32.76
        },
        {
            "file": "182_8.mp3",
            "duration": 35.2
        },
        {
            "file": "182_9.mp3",
            "duration": 31.09
        },
        {
            "file": "182_10.mp3",
            "duration": 34.61
        },
        {
            "file": "182_11.mp3",
            "duration": 35.35
        },
        {
            "file": "182_12.mp3",
            "duration": 30.47
        },
        {
            "file": "182_13.mp3",
            "duration": 33.37
        },
        {
            "file": "182_14.mp3",
            "duration": 36.91
        },
        {
            "file": "182_15.mp3",
            "duration": 35.83
        },
        {
            "file": "182_16.mp3",
            "duration": 31.72
        },
        {
            "file": "182_17.mp3",
            "duration": 31.39
        },
        {
            "file": "182_18.mp3",
            "duration": 34.5
        },
        {
            "file": "182_19.mp3",
            "duration": 40.73
        },
        {
            "file": "182_20.mp3",
            "duration": 30.01
        },
        {
            "file": "182_21.mp3",
            "duration": 43.24
        },
        {
            "file": "182_22.mp3",
            "duration": 35.61
        },
        {
            "file": "182_23.mp3",
            "duration": 38.22
        },
        {
            "file": "182_24.mp3",
            "duration": 33.08
        },
        {
            "file": "182_25.mp3",
            "duration": 15.32
        }
    ],
    "total_files": 25,
    "total_duration": 843.41
}