{
    "folder": "441",
    "audio_files": [
        {
            "file": "441_1.wav",
            "duration": 33.67
        },
        {
            "file": "441_2.wav",
            "duration": 31.32
        },
        {
            "file": "441_3.wav",
            "duration": 34.93
        },
        {
            "file": "441_4.wav",
            "duration": 34.27
        },
        {
            "file": "441_5.wav",
            "duration": 31.43
        },
        {
            "file": "441_6.wav",
            "duration": 24.46
        },
        {
            "file": "441_7.wav",
            "duration": 33.12
        },
        {
            "file": "441_8.wav",
            "duration": 27.04
        },
        {
            "file": "441_9.wav",
            "duration": 32.15
        },
        {
            "file": "441_10.wav",
            "duration": 35.92
        },
        {
            "file": "441_11.wav",
            "duration": 30.02
        },
        {
            "file": "441_12.wav",
            "duration": 36.72
        },
        {
            "file": "441_13.wav",
            "duration": 36.14
        },
        {
            "file": "441_14.wav",
            "duration": 27.65
        },
        {
            "file": "441_15.wav",
            "duration": 31.33
        },
        {
            "file": "441_16.wav",
            "duration": 31.27
        },
        {
            "file": "441_17.wav",
            "duration": 32.15
        },
        {
            "file": "441_18.wav",
            "duration": 27.85
        },
        {
            "file": "441_19.wav",
            "duration": 31.91
        },
        {
            "file": "441_20.wav",
            "duration": 28.34
        },
        {
            "file": "441_21.wav",
            "duration": 25.39
        },
        {
            "file": "441_22.wav",
            "duration": 29.27
        },
        {
            "file": "441_23.wav",
            "duration": 30.94
        },
        {
            "file": "441_24.wav",
            "duration": 30.49
        },
        {
            "file": "441_25.wav",
            "duration": 27.33
        },
        {
            "file": "441_26.wav",
            "duration": 32.62
        },
        {
            "file": "441_27.wav",
            "duration": 32.6
        },
        {
            "file": "441_28.wav",
            "duration": 36.13
        },
        {
            "file": "441_29.wav",
            "duration": 30.37
        },
        {
            "file": "441_30.wav",
            "duration": 30.57
        },
        {
            "file": "441_31.wav",
            "duration": 32.12
        }
    ],
    "total_files": 31,
    "total_duration": 969.52
}