{
    "folder": "217",
    "audio_files": [
        {
            "file": "217_1.mp3",
            "duration": 32.48
        },
        {
            "file": "217_2.mp3",
            "duration": 33.21
        },
        {
            "file": "217_3.mp3",
            "duration": 39.11
        },
        {
            "file": "217_4.mp3",
            "duration": 31.0
        },
        {
            "file": "217_5.mp3",
            "duration": 23.11
        },
        {
            "file": "217_6.mp3",
            "duration": 31.47
        },
        {
            "file": "217_7.mp3",
            "duration": 33.72
        },
        {
            "file": "217_8.mp3",
            "duration": 21.66
        },
        {
            "file": "217_9.mp3",
            "duration": 30.25
        },
        {
            "file": "217_10.mp3",
            "duration": 32.25
        },
        {
            "file": "217_11.mp3",
            "duration": 31.84
        },
        {
            "file": "217_12.mp3",
            "duration": 27.98
        },
        {
            "file": "217_13.mp3",
            "duration": 31.07
        },
        {
            "file": "217_14.mp3",
            "duration": 30.21
        },
        {
            "file": "217_15.mp3",
            "duration": 31.37
        },
        {
            "file": "217_16.mp3",
            "duration": 32.76
        },
        {
            "file": "217_17.mp3",
            "duration": 33.72
        },
        {
            "file": "217_18.mp3",
            "duration": 28.85
        },
        {
            "file": "217_19.mp3",
            "duration": 32.85
        },
        {
            "file": "217_20.mp3",
            "duration": 33.58
        },
        {
            "file": "217_21.mp3",
            "duration": 26.04
        },
        {
            "file": "217_22.mp3",
            "duration": 32.48
        },
        {
            "file": "217_23.mp3",
            "duration": 8.77
        }
    ],
    "total_files": 23,
    "total_duration": 689.78
}